Metadata-Version: 2.1
Name: NT-TextFileLoader
Version: 1.1.3
Summary: Python library to extract text from various file formats. the supported file formats are "JPG","JPEG","PNG","PDF","DOCX","DOC" and "TEXT".
Author: Vishnu.D
Author-email: "Vishnu.D" <vishnu.d@narmtech.com>
License: MIT
Keywords: text extractor,text loader,load text file,read text from pdf,load text from DOC,load text from DOCX,read text from images
Classifier: Programming Language :: Python :: 3
Classifier: License :: OSI Approved :: MIT License
Classifier: Operating System :: OS Independent
Requires-Python: >=3.10
License-File: LICENSE.txt
